LICENSE
MANIFEST.in
README.md
setup.py
pysimplevcs/__init__.py
pysimplevcs/git.py
pysimplevcs/git_util.py
pysimplevcs/hg.py
pysimplevcs.egg-info/PKG-INFO
pysimplevcs.egg-info/SOURCES.txt
pysimplevcs.egg-info/dependency_links.txt
pysimplevcs.egg-info/not-zip-safe
pysimplevcs.egg-info/requires.txt
pysimplevcs.egg-info/top_level.txt